README.rst
setup.py
django_gibson_sessions.egg-info/PKG-INFO
django_gibson_sessions.egg-info/SOURCES.txt
django_gibson_sessions.egg-info/dependency_links.txt
django_gibson_sessions.egg-info/not-zip-safe
django_gibson_sessions.egg-info/requires.txt
django_gibson_sessions.egg-info/top_level.txt
gibson_sessions/__init__.py
gibson_sessions/sessions.py