Metadata-Version: 1.1
Name: django-gibson-sessions
Version: 0.8
Summary: Gibson session backend for Django
Home-page: https://github.com/mikalaiyurkin/django-gibson-sessions
Author: Mikalai Yurkin
Author-email: yurkin.mikalai@gmail.com
License: MIT
Keywords: django,gibson,sessions,
Platform: UNKNOWN
Classifier: Programming Language :: Python :: 2
Classifier: Programming Language :: Python :: 3
Classifier: Topic :: Software Development :: Libraries :: Python Modules
Classifier: Framework :: Django
Classifier: Environment :: Web Environment
